Metadata-Version: 2.1
Name: odoo-addon-website_legal_page
Version: 18.0.1.0.0.2
Requires-Python: >=3.10
Requires-Dist: odoo==18.0.*
Summary: Website Legal Page
Home-page: https://github.com/OCA/website
License: AGPL-3
Author: Tecnativa, LasLabs, Nicolas JEUDY, Odoo Community Association (OCA)
Author-email: support@odoo-community.org
Classifier: Programming Language :: Python
Classifier: Framework :: Odoo
Classifier: Framework :: Odoo :: 18.0
Classifier: License :: OSI Approved :: GNU Affero General Public License v3
